deriva/__init__.py
deriva/utils/__init__.py
deriva/utils/catalog/__init__.py
deriva/utils/catalog/version.py
deriva/utils/catalog/components/__init__.py
deriva/utils/catalog/components/configure_catalog.py
deriva/utils/catalog/components/deriva_catalog.py
deriva/utils/catalog/components/deriva_model.py
deriva/utils/catalog/components/navbar.py
deriva/utils/catalog/components/visible_column.py
deriva/utils/catalog/manage/__init__.py
deriva/utils/catalog/manage/common_tables.py
deriva/utils/catalog/manage/config.py
deriva/utils/catalog/manage/deriva_csv.py
deriva/utils/catalog/manage/deriva_file_templates.py
deriva/utils/catalog/manage/dump_catalog.py
deriva/utils/catalog/manage/globus_groups.py
deriva/utils/catalog/manage/graph_catalog.py
deriva/utils/catalog/manage/update_catalog.py
deriva/utils/catalog/manage/utils.py
extra_tests/deriva/__init__.py
extra_tests/deriva/utils/__init__.py
extra_tests/deriva/utils/catalog/__init__.py
extra_tests/deriva/utils/catalog/manage/__init__.py
extra_tests/deriva/utils/catalog/manage/config.py
extra_tests/deriva/utils/catalog/manage/test_derivaCSV.py
tests/deriva/__init__.py
tests/deriva/utils/__init__.py
tests/deriva/utils/catalog/__init__.py
tests/deriva/utils/catalog/test_utils.py
tests/deriva/utils/catalog/components/__init__.py
tests/deriva/utils/catalog/components/test_configure_catalog.py
tests/deriva/utils/catalog/components/test_deriva_model.py
tests/deriva/utils/catalog/manage/__init__.py
tests/deriva/utils/catalog/manage/test_catalogUpdater.py
tests/deriva/utils/catalog/manage/test_derivaCatalogToString.py
deriva_catalog_manage-0.9.2.dist-info/LICENSE
deriva_catalog_manage-0.9.2.dist-info/METADATA
deriva_catalog_manage-0.9.2.dist-info/WHEEL
deriva_catalog_manage-0.9.2.dist-info/entry_points.txt
deriva_catalog_manage-0.9.2.dist-info/top_level.txt
deriva_catalog_manage-0.9.2.dist-info/RECORD
