Metadata-Version: 2.1
Name: deriva-catalog-manage
Version: 0.9.2
Summary: DERIVA catalog management utilities built on deriva-py.
Home-page: https://github.com/informatics-isi-edu/deriva-catalog-manage
Author: USC Information Sciences Institute, Informatics Systems Research Division
Author-email: isrd-support@isi.edu
Maintainer: USC Information Sciences Institute, Informatics Systems Research Division
Maintainer-email: isrd-support@isi.edu
License: Apache 2.0
Classifier: Intended Audience :: Science/Research
Classifier: Intended Audience :: Developers
Classifier: License :: OSI Approved :: Apache Software License
Classifier: Operating System :: POSIX
Classifier: Operating System :: MacOS :: MacOS X
Classifier: Operating System :: Microsoft :: Windows
Classifier: Programming Language :: Python
Classifier: Programming Language :: Python :: 3.8
Classifier: Programming Language :: Python :: 3.9
Classifier: Programming Language :: Python :: 3.10
Classifier: Programming Language :: Python :: 3.11
Requires-Python: >=3.6
License-File: LICENSE
Requires-Dist: requests
Requires-Dist: graphviz
Requires-Dist: tabulate
Requires-Dist: yapf
Requires-Dist: deriva >=1.4.1
Provides-Extra: csv
Requires-Dist: goodtables ; extra == 'csv'
Requires-Dist: python-dateutil ; extra == 'csv'
Requires-Dist: simpleeval ; extra == 'csv'
